howigothere/__init__.py
howigothere/main.py
howigothere/py.typed
howigothere/utils.py
howigothere/version.py
howigothere-1.1.0.dist-info/METADATA
howigothere-1.1.0.dist-info/WHEEL
howigothere-1.1.0.dist-info/RECORD
