Metadata-Version: 2.1
Name: howigothere
Version: 1.1.0
Summary: Python module to create a condensed stack preview
Project-URL: Homepage, https://github.com/vsego/howigothere
Project-URL: Bug Tracker, https://github.com/vsego/howigothere/issues
Project-URL: Changelog, https://github.com/vsego/howigothere/blob/master/CHANGELOG.md
Author-email: Vedran Sego <vsego@vsego.org>
License-Expression: MIT
Keywords: debugging
Classifier: Development Status :: 5 - Production/Stable
Classifier: Intended Audience :: Developers
Classifier: Operating System :: OS Independent
Classifier: Programming Language :: Python :: 3.6
Classifier: Topic :: Software Development :: Libraries :: Python Modules
Classifier: Topic :: Utilities
Classifier: Typing :: Typed
Requires-Python: >=3.6
Requires-Dist: settings-collector>=1.2.1
